kazopdf/__init__.py
kazopdf/pdf2image.py
kazopdf/pdf2text.py
kazopdf-1.0.dist-info/License
kazopdf-1.0.dist-info/METADATA
kazopdf-1.0.dist-info/WHEEL
kazopdf-1.0.dist-info/top_level.txt
kazopdf-1.0.dist-info/RECORD
