Metadata-Version: 2.1
Name: kazopdf
Version: 1.0
Summary: This is the homepage of our project.
Home-page: UNKNOWN
Author: UNKNOWN
Author-email: UNKNOWN
License: UNKNOWN
Platform: UNKNOWN
